keystone_assimilation/__init__.py
keystone_assimilation/cli.py
keystone_assimilation/collect.py
keystone_assimilation/config.py
keystone_assimilation/ingest.py
keystone_assimilation/models.py
keystone_assimilation/states.py
keystone_assimilation/analysis/__init__.py
keystone_assimilation/analysis/coverage_map.py
keystone_assimilation/analysis/dependency_graph.py
keystone_assimilation/analysis/python_ast.py
keystone_assimilation-0.1.14.dist-info/METADATA
keystone_assimilation-0.1.14.dist-info/WHEEL
keystone_assimilation-0.1.14.dist-info/entry_points.txt
keystone_assimilation-0.1.14.dist-info/RECORD
