Metadata-Version: 2.4
Name: keystone-assimilation
Version: 0.1.14
Summary: Keystone assimilation tooling for forward-only governance
Author: Keystone
License: Proprietary
Requires-Python: >=3.10
Requires-Dist: pyyaml>=6.0.3
Requires-Dist: requests>=2.32.5
Provides-Extra: dev
Requires-Dist: build>=1.3.0; extra == 'dev'
Requires-Dist: commitizen>=4.10.1; extra == 'dev'
Requires-Dist: pytest-cov>=7.0.0; extra == 'dev'
Requires-Dist: pytest>=9.0.2; extra == 'dev'
Requires-Dist: ruff>=0.14.10; extra == 'dev'
Requires-Dist: twine>=5.1.1; extra == 'dev'
